aws_cf_custom_resources/__init__.py
aws_cf_custom_resources/abstract_custom_service.py
aws_cf_custom_resources/config_params.py
aws_cf_custom_resources/custom_resources_builder.py
aws_cf_custom_resources/global_config_manager.py
aws_cf_custom_resources/cognito_client_secret/__init__.py
aws_cf_custom_resources/cognito_client_secret/resource.py
aws_cf_custom_resources/cognito_client_secret/service.py
aws_cf_custom_resources/cognito_client_secret/package/__init__.py
aws_cf_custom_resources/cognito_client_secret/package/index.py
aws_cf_custom_resources/cognito_client_secret/package/setup.py
aws_cf_custom_resources/cognito_domain/__init__.py
aws_cf_custom_resources/cognito_domain/resource.py
aws_cf_custom_resources/cognito_domain/service.py
aws_cf_custom_resources/cognito_domain/package/__init__.py
aws_cf_custom_resources/cognito_domain/package/index.py
aws_cf_custom_resources/cognito_domain/package/setup.py
aws_cf_custom_resources/cognito_facebook/__init__.py
aws_cf_custom_resources/cognito_facebook/resource.py
aws_cf_custom_resources/cognito_facebook/service.py
aws_cf_custom_resources/cognito_facebook/package/__init__.py
aws_cf_custom_resources/cognito_facebook/package/index.py
aws_cf_custom_resources/cognito_facebook/package/setup.py
aws_cf_custom_resources/deployment_group/__init__.py
aws_cf_custom_resources/deployment_group/resource.py
aws_cf_custom_resources/deployment_group/service.py
aws_cf_custom_resources/deployment_group/package/__init__.py
aws_cf_custom_resources/deployment_group/package/fixer.py
aws_cf_custom_resources/deployment_group/package/group.py
aws_cf_custom_resources/deployment_group/package/index.py
aws_cf_custom_resources/deployment_group/package/setup.py
aws_cf_custom_resources/ecs_service/__init__.py
aws_cf_custom_resources/ecs_service/resource.py
aws_cf_custom_resources/ecs_service/service.py
aws_cf_custom_resources/ecs_service/package/__init__.py
aws_cf_custom_resources/ecs_service/package/fixer.py
aws_cf_custom_resources-1.0.2.dist-info/LICENSE.txt
aws_cf_custom_resources-1.0.2.dist-info/METADATA
aws_cf_custom_resources-1.0.2.dist-info/WHEEL
aws_cf_custom_resources-1.0.2.dist-info/top_level.txt
aws_cf_custom_resources-1.0.2.dist-info/RECORD
