Metadata-Version: 2.1
Name: aws-cf-custom-resources
Version: 1.0.2
Summary: Container library which contains various custom resources for AWS CloudFormation.
Home-page: https://github.com/laimonassutkus/AwsCfCustomResources
Author: Laimonas Sutkus
Author-email: laimonas.sutkus@gmail.com
License: GNU GENERAL PUBLIC LICENSE Version 3
Keywords: AWS SDK CloudFormation Infrastructure Cloud CustomResource
Platform: UNKNOWN
Classifier: Programming Language :: Python :: 3
Classifier: Programming Language :: Python :: 3.5
Classifier: Programming Language :: Python :: 3.6
Classifier: Operating System :: OS Independent
Requires-Dist: boto3
Requires-Dist: botocore
Requires-Dist: troposphere
Requires-Dist: cfnresponse
Requires-Dist: aws-lambda
